tests/unit/__init__.py
tests/unit/conftest.py
tests/unit/test_1000g_vcf.py
tests/unit/test_annotator.py
tests/unit/test_cli.py
tests/unit/test_coding_conventions.py
tests/unit/test_collect_vcfs.py
tests/unit/test_metakb.py
tests/unit/test_translator.py
tests/unit/test_vcf_to_gnomad.py
vrs_anvil/__init__.py
vrs_anvil/annotator.py
vrs_anvil/cli.py
vrs_anvil/collector.py
vrs_anvil/translator.py
vrs_anvil-0.0.1rc2.dist-info/LICENSE.md
vrs_anvil-0.0.1rc2.dist-info/METADATA
vrs_anvil-0.0.1rc2.dist-info/WHEEL
vrs_anvil-0.0.1rc2.dist-info/entry_points.txt
vrs_anvil-0.0.1rc2.dist-info/top_level.txt
vrs_anvil-0.0.1rc2.dist-info/RECORD
