Metadata-Version: 2.1
Name: vrs_anvil
Version: 0.0.1rc2
Summary: Commons utilities
Home-page: https://github.com/ohsu-comp-bio/vrs_anvil_toolkit
Author: Ellrott Lab
Project-URL: Bug Reports, https://github.com/ohsu-comp-bio/vrs_anvil_toolkit/issues
Project-URL: Source, https://github.com/ohsu-comp-bio/vrs_anvil_toolkit
Keywords: anvil terra bioinformatics
Classifier: Development Status :: 4 - Beta
Classifier: Intended Audience :: Developers
Classifier: Topic :: Software Development :: Build Tools
Classifier: License :: OSI Approved :: MIT License
Classifier: Programming Language :: Python :: 3.10
Requires-Python: >=3.10, <4
License-File: LICENSE.md
Requires-Dist: ga4gh.vrs[extras] ==2.0.0a5
Requires-Dist: diskcache
Requires-Dist: biocommons.seqrepo
Requires-Dist: glom
Requires-Dist: click
Requires-Dist: pyyaml
Requires-Dist: google
Requires-Dist: requests
Requires-Dist: boto3
Requires-Dist: tqdm
Requires-Dist: google-cloud-storage
Requires-Dist: psutil
